tormysql/__init__.py
tormysql/client.py
tormysql/connections.py
tormysql/cursor.py
tormysql/helpers.py
tormysql/log.py
tormysql/pool.py
tormysql/util.py
tormysql-0.3.5.dist-info/DESCRIPTION.rst
tormysql-0.3.5.dist-info/METADATA
tormysql-0.3.5.dist-info/RECORD
tormysql-0.3.5.dist-info/WHEEL
tormysql-0.3.5.dist-info/metadata.json
tormysql-0.3.5.dist-info/top_level.txt
