Metadata-Version: 2.0
Name: tormysql
Version: 0.3.5
Summary: Tornado asynchronous MySQL Driver
Home-page: https://github.com/snower/TorMySQL
Author: snower, mosquito
Author-email: sujian199@gmail.com, me@mosquito.su
License: MIT
Keywords: tornado,mysql
Platform: UNKNOWN
Requires-Dist: PyMySQL (>=0.7.10)
Requires-Dist: greenlet (>=0.4.2)
Requires-Dist: tornado (>=4.5)
